text_utils/__init__.py
text_utils/text_utils.py
text_utils-0.0.5.dist-info/LICENCE
text_utils-0.0.5.dist-info/METADATA
text_utils-0.0.5.dist-info/WHEEL
text_utils-0.0.5.dist-info/top_level.txt
text_utils-0.0.5.dist-info/RECORD
